sensivalidate/__init__.py
sensivalidate/sensivalidate.py
sensivalidate-1.0.0.dist-info/LICENSE
sensivalidate-1.0.0.dist-info/METADATA
sensivalidate-1.0.0.dist-info/WHEEL
sensivalidate-1.0.0.dist-info/top_level.txt
sensivalidate-1.0.0.dist-info/RECORD
