Metadata-Version: 2.2
Name: sensivalidate
Version: 1.0.0
Summary: A module to find credit card, UK bank account, sort code and postcode in text
Home-page: https://github.com/rootifera/sensivalidate
Author: Omur Ozbahceliler
Author-email: omur@rootifera.org
Classifier: Programming Language :: Python :: 3
Classifier: License :: OSI Approved :: MIT License
Classifier: Operating System :: OS Independent
License-File: LICENSE
Requires-Dist: creditcard==1.0.2
Dynamic: author
Dynamic: author-email
Dynamic: classifier
Dynamic: description
Dynamic: description-content-type
Dynamic: home-page
Dynamic: requires-dist
Dynamic: summary
